prepars/__init__.py
prepars/normalizer.py
prepars/regexer.py
prepars/spacing.py
prepars/verb.py
prepars/PVC/Data/TXT/all_verbs.txt
prepars/PVC/Data/TXT/prefix.txt
prepars/PVC/Data/TXT/replacement.json
prepars/PVC/Data/TXT/suffix.csv
prepars-0.0.4.dist-info/LICENSE
prepars-0.0.4.dist-info/METADATA
prepars-0.0.4.dist-info/WHEEL
prepars-0.0.4.dist-info/top_level.txt
prepars-0.0.4.dist-info/RECORD
