Metadata-Version: 2.1
Name: prepars
Version: 0.0.4
Summary: The prePars is a Python package for NLP preprocessing on Persian Language.
Author-email: Mahdi Akhi <mahdiakhy@gmail.com>, Amir Pourmand <pourmand1376@gmail.com>, Pouya Khani <pouya.khani11@gmail.com>
License: Copyright (c) 2018 The Python Packaging Authority        
Project-URL: Homepage, https://github.com/pam-lab/PrePars/
Project-URL: Bug Tracker, https://github.com/pam-lab/PrePars/issues
Classifier: Programming Language :: Python :: 3
Classifier: License :: OSI Approved :: MIT License
Classifier: Operating System :: OS Independent
Requires-Python: >=3.0
License-File: LICENSE
